[
  {
    "type": "dropDown",
    "label": "P10 multi-channel GEN1 pipette mount",
    "name": "p10_multi_mount",
    "options": [
      { "label": "left", "value": "left" },
      { "label": "right", "value": "right" }
    ]
  },
  {
    "type": "int",
    "label": "number of samples (1-96, processed in columns of 8)",
    "name": "num_samples",
    "default": 96
  },
  {
    "type": "dropDown",
    "label": "replicate factor",
    "name": "num_reps",
    "options": [
      { "label": "duplicate", "value": "duplicate"},
      { "label": "quadruplicate", "value": "quadruplicate"}
    ]
  },
  {
    "type": "int",
    "label": "number of mastermixes (if processing duplicates)",
    "name": "num_mm",
    "default": 2
  }
]
