[
  {
    "type": "textFile",
    "label": "input .csv file",
    "name": "input_csv",
    "default": "Sample Conc. (mg/ml),Sample Volume, mL (a),water, mL (b),Buffer 1, mL (c),Probe,Probe well, mL (d),Total Vol., mL Sum (a,b,c,d)\n1,40,50,10,5,A3,105\n2.2,18.2,71.8,10,5,A3,105\n2.03,19.7,70.3,10,5,A4,105\n"
  },
  {
    "type": "dropDown",
    "label": "P300 single GEN2 mount",
    "name": "p300_mount",
    "options": [
      {"label": "left", "value": "left"},
      {"label": "right", "value": "right"}
    ]
  },
  {
    "type": "dropDown",
    "label": "P20 single GEN2 mount",
    "name": "p20_mount",
    "options": [
      {"label": "right", "value": "right"},
      {"label": "left", "value": "left"}
    ]
  }
]
